multiple_desktop_clocks/__init__.py
multiple_desktop_clocks/about.py
multiple_desktop_clocks/desktop.py
multiple_desktop_clocks/program.py
multiple_desktop_clocks/icons/logo.png
multiple_desktop_clocks/modules/__init__.py
multiple_desktop_clocks/modules/configure.py
multiple_desktop_clocks/modules/wabout.py
multiple_desktop_clocks-0.1.3.dist-info/licenses/LICENSE
multiple_desktop_clocks-0.1.3.dist-info/METADATA
multiple_desktop_clocks-0.1.3.dist-info/WHEEL
multiple_desktop_clocks-0.1.3.dist-info/entry_points.txt
multiple_desktop_clocks-0.1.3.dist-info/top_level.txt
multiple_desktop_clocks-0.1.3.dist-info/RECORD
